RobertJN64TemplatePackage/__init__.py
RobertJN64TemplatePackage/afile.txt
robertjn64templatepackage-1.1.5.dist-info/licenses/LICENSE
robertjn64templatepackage-1.1.5.dist-info/METADATA
robertjn64templatepackage-1.1.5.dist-info/WHEEL
robertjn64templatepackage-1.1.5.dist-info/top_level.txt
robertjn64templatepackage-1.1.5.dist-info/RECORD
