Metadata-Version: 2.4
Name: RobertJN64TemplatePackage
Version: 1.1.5
Summary: A template for package structure, deployment, and testing
Home-page: https://github.com/RobertJN64/RobertJN64TemplatePackage
Author: Robert Nies
Author-email: robertjnies@gmail.com
License: MIT
Classifier: Programming Language :: Python
Classifier: Programming Language :: Python :: 3
Classifier: Programming Language :: Python :: 3 :: Only
Classifier: Programming Language :: Python :: 3.10
Classifier: Programming Language :: Python :: 3.11
Classifier: Programming Language :: Python :: 3.12
Classifier: Programming Language :: Python :: 3.13
Classifier: Programming Language :: Python :: 3.14
Requires-Python: >=3.10
License-File: LICENSE
Requires-Dist: requests>=2.26.0
Provides-Extra: bonus
Requires-Dist: tabulate; extra == "bonus"
Provides-Extra: dev
Requires-Dist: pytest; extra == "dev"
Dynamic: license-file
